log_utils/__init__.py
log_utils/helper.py
log_utils/data_logger/__init__.py
log_utils/data_logger/converter_dataclass.py
log_utils/data_logger/converter_matplotlib.py
log_utils/data_logger/converter_numpy_image.py
log_utils/data_logger/converters.py
log_utils/data_logger/core.py
log_utils/data_logger/handlers.py
log_utils/data_logger/contrib/__init__.py
log_utils/data_logger/contrib/plotly_converter.py
log_utils-0.4.1.dist-info/LICENSE.txt
log_utils-0.4.1.dist-info/METADATA
log_utils-0.4.1.dist-info/WHEEL
log_utils-0.4.1.dist-info/top_level.txt
log_utils-0.4.1.dist-info/RECORD
