Metadata-Version: 2.1
Name: log_utils
Version: 0.4.1
Summary: Utils for generic python logging package
Home-page: https://github.com/wolf1986/log_utils
Author: Willy Polychenko
Author-email: wolf1986@gmail.com
License: UNKNOWN
Platform: UNKNOWN
Classifier: Programming Language :: Python :: 3
Classifier: Programming Language :: Python :: 3.6
Classifier: Programming Language :: Python :: 3.7
Classifier: Programming Language :: Python :: 3.8
Classifier: Programming Language :: Python :: 3.9
Classifier: Programming Language :: Python :: 3.10
Requires-Python: >=3.6
License-File: LICENSE.txt
